MANIFEST.in
README.rst
setup.py
spam/__init__.py
spam/spamhaus.py
spam/surbl.py
spam/three-level-tlds
spam/two-level-tlds
spam_blocklists.egg-info/PKG-INFO
spam_blocklists.egg-info/SOURCES.txt
spam_blocklists.egg-info/dependency_links.txt
spam_blocklists.egg-info/top_level.txt