Metadata-Version: 1.1
Name: spam-blocklists
Version: 0.9.3
Summary: Spam related services interface
Home-page: https://github.com/fmarani/spam
Author: Federico Marani
Author-email: flagzeta@gmail.com
License: UNKNOWN
Platform: UNKNOWN
Classifier: Intended Audience :: Developers
Classifier: Operating System :: OS Independent
Classifier: Programming Language :: Python
Classifier: Topic :: Software Development :: Libraries
